{
  "gdp_per_capita": 14639.5046929186,
  "population": 12025.0,
  "internet_users_pct": 83.01170349,
  "gdp_growth": 2.14285714285656,
  "trade_pct_gdp": 165.441176470588,
  "gov_revenue_pct_gdp": 115.548018359375,
  "capital_city": "Yaren District",
  "income_level": "High income",
  "latitude": "-0.5477",
  "longitude": "166.920867",
  "forest_area_pct": 0.0,
  "co2_per_capita": 4.9893417,
  "food_insecurity_pct": 9.2,
  "meat_production_tonnes": 78.52,
  "fish_consumption_kg_pc": 26.016201
}